{
  "updated": "2026-04-06T14:38:19Z",
  "count": 32,
  "articles": [
    {
      "title": "'They don't have any role': Iran Supreme Leader's representative in India refutes Pakistan's mediation role in West Asia conflict",
      "url": "https://economictimes.indiatimes.com/news/international/world-news/they-dont-have-any-role-iran-supreme-leaders-representative-in-india-refutes-pakistans-mediation-role-in-west-asia-conflict/articleshow/130041180.cms",
      "source": "The Times of India",
      "publishedAt": "2026-04-05T14:34:52Z",
      "_cat": "iran",
      "_label": "Iran War"
    },
    {
      "title": "Despite the Netanyahu Government's Promises, the IDF Admits It Can't Disarm Hezbollah - Haaretz",
      "url": "https://slashdot.org/firehose.pl?op=view&amp;id=181272540",
      "source": "Slashdot.org",
      "publishedAt": "2026-04-05T14:32:38Z",
      "_cat": "lebanon",
      "_label": "Lebanon"
    },
    {
      "title": "The ongoing war with Iran: Letters to the Editor — April 6, 2026",
      "url": "https://nypost.com/2026/04/05/opinion/the-ongoing-war-with-iran-letters/",
      "source": "New York Post",
      "publishedAt": "2026-04-05T14:21:18Z",
      "_cat": "iran",
      "_label": "Iran War"
    },
    {
      "title": "Lebanese president defends diplomatic outreach to Israel",
      "url": "https://www.irishtimes.com/world/middle-east/2026/04/05/lebanese-president-defends-diplomatic-outreach-to-israel/",
      "source": "The Irish Times",
      "publishedAt": "2026-04-05T14:16:51Z",
      "_cat": "iran",
      "_label": "Iran War"
    },
    {
      "title": "Israel renews strikes on Lebanon, forces Syria border crossing to close",
      "url": "https://www.channelnewsasia.com/world/israel-strike-lebanon-syria-border-crossing-close-6037636",
      "source": "CNA",
      "publishedAt": "2026-04-05T13:40:43Z",
      "_cat": "lebanon",
      "_label": "Lebanon"
    },
    {
      "title": "Strait of Hormuz puzzle and Donald Trump Truth Social threats to blow up power plants, bridges: Iran war braces for decisive moment as deadline nears",
      "url": "https://economictimes.indiatimes.com/news/international/us/strait-of-hormuz-puzzle-and-donald-trump-threats-to-blow-up-power-plants-bridges-iran-war-braces-for-decisive-moment-as-deadline-nears/articleshow/130040251.cms",
      "source": "The Times of India",
      "publishedAt": "2026-04-05T13:32:58Z",
      "_cat": "iran",
      "_label": "Iran War"
    },
    {
      "title": "American Greatness, American Barbarism",
      "url": "http://www.rollingstone.com/politics/political-commentary/american-greatness-artemis-ii-american-barbarism-iran-war-1235541998/",
      "source": "Rolling Stone",
      "publishedAt": "2026-04-05T13:00:00Z",
      "_cat": "iran",
      "_label": "Iran War"
    },
    {
      "title": "A brief history of the Israeli nuclear program, the open secret at the heart of the Iran war",
      "url": "https://mondoweiss.net/2026/04/a-brief-history-of-the-israeli-nuclear-program-the-open-secret-at-the-heart-of-the-iran-war/",
      "source": "Mondoweiss",
      "publishedAt": "2026-04-05T13:00:00Z",
      "_cat": "nuclear",
      "_label": "Nuclear"
    },
    {
      "title": "Pope calls for peace as M’East conflict casts shadow on Easter",
      "url": "https://punchng.com/pope-calls-for-peace-as-meast-conflict-casts-shadow-on-easter/",
      "source": "The Punch",
      "publishedAt": "2026-04-05T12:36:07Z",
      "_cat": "lebanon",
      "_label": "Lebanon"
    },
    {
      "title": "Trump threatens Iran with ‘Power Plant Day’ if Hormuz stays shut",
      "url": "https://economictimes.indiatimes.com/news/defence/trump-threatens-iran-with-power-plant-day-if-hormuz-stays-shut/articleshow/130039085.cms",
      "source": "The Times of India",
      "publishedAt": "2026-04-05T12:20:14Z",
      "_cat": "iran",
      "_label": "Iran War"
    },
    {
      "title": "Trump Risks Confidence in US Role as Guardian of Global Shipping",
      "url": "https://financialpost.com/pmn/business-pmn/trump-risks-confidence-in-us-role-as-guardian-of-global-shipping",
      "source": "Financial Post",
      "publishedAt": "2026-04-05T12:19:33Z",
      "_cat": "iran",
      "_label": "Iran War"
    },
    {
      "title": "US-Israeli aggression on Iran: What happened on 37th day of the imposed war",
      "url": "https://www.globalsecurity.org/wmd/library/news/iran/2026/04/iran-260405-presstv02.htm",
      "source": "Globalsecurity.org",
      "publishedAt": "2026-04-05T12:00:00Z",
      "_cat": "iran",
      "_label": "Iran War"
    },
    {
      "title": "Missing US pilot rescued in Iran; war course remains unchanged as US doubles down to recoup sunk costs: Chinese experts",
      "url": "https://www.globalsecurity.org/wmd/library/news/iran/2026/04/iran-260405-globaltimes02.htm",
      "source": "Globalsecurity.org",
      "publishedAt": "2026-04-05T12:00:00Z",
      "_cat": "iran",
      "_label": "Iran War"
    },
    {
      "title": "IRGC Navy pounds key US-Israeli targets in wave 97 of Operation True Promise 4",
      "url": "https://www.globalsecurity.org/wmd/library/news/iran/2026/04/iran-260405-presstv05.htm",
      "source": "Globalsecurity.org",
      "publishedAt": "2026-04-05T12:00:00Z",
      "_cat": "iran",
      "_label": "Iran War"
    },
    {
      "title": "Israel launches deadly airstrikes on Beirut after Hezbollah targets warship",
      "url": "https://www.globalsecurity.org/military/library/news/2026/04/mil-260405-presstv01.htm",
      "source": "Globalsecurity.org",
      "publishedAt": "2026-04-05T12:00:00Z",
      "_cat": "lebanon",
      "_label": "Lebanon"
    },
    {
      "title": "Middle East War Casualty Lists Updated",
      "url": "https://www.globalsecurity.org/wmd/library/news/iran/2026/04/iran-260405-rferl01.htm",
      "source": "Globalsecurity.org",
      "publishedAt": "2026-04-05T12:00:00Z",
      "_cat": "lebanon",
      "_label": "Lebanon"
    },
    {
      "title": "Israel Targets 'Hezbollah Infrastructure,' Strikes Hit Beirut And Southern Lebanon",
      "url": "https://www.globalsecurity.org/military/library/news/2026/04/mil-260405-rferl05.htm",
      "source": "Globalsecurity.org",
      "publishedAt": "2026-04-05T12:00:00Z",
      "_cat": "lebanon",
      "_label": "Lebanon"
    },
    {
      "title": "Sunday: Hili dialogue",
      "url": "https://whyevolutionistrue.com/2026/04/05/sunday-hili-dialogue-580/",
      "source": "Whyevolutionistrue.com",
      "publishedAt": "2026-04-05T11:45:16Z",
      "_cat": "ukraine",
      "_label": "Ukraine"
    },
    {
      "title": "Watch: IDF strikes Hezbollah infrastructure",
      "url": "https://www.israelnationalnews.com/news/425046",
      "source": "Israelnationalnews.com",
      "publishedAt": "2026-04-05T10:26:54Z",
      "_cat": "lebanon",
      "_label": "Lebanon"
    },
    {
      "title": "Why Trump Thinks He Can Walk Away From the Strait of Hormuz",
      "url": "https://www.theatlantic.com/ideas/2026/04/energy-price-consequences-iran-war/686687/",
      "source": "The Atlantic",
      "publishedAt": "2026-04-05T10:00:00Z",
      "_cat": "ukraine",
      "_label": "Ukraine"
    },
    {
      "title": "In Lebanon, more than 50 medics have been killed by Israel. Some say they're targeted",
      "url": "https://www.npr.org/2026/04/05/nx-s1-5763606/lebanon-medics-killed-targeted-israel",
      "source": "NPR",
      "publishedAt": "2026-04-05T10:00:00Z",
      "_cat": "lebanon",
      "_label": "Lebanon"
    },
    {
      "title": "True Promise 4: Iran and resistance axis ops. against US-Israeli assets on April 4",
      "url": "https://www.globalsecurity.org/wmd/library/news/iran/2026/04/iran-260404-presstv03.htm",
      "source": "Globalsecurity.org",
      "publishedAt": "2026-04-05T08:52:01Z",
      "_cat": "lebanon",
      "_label": "Lebanon"
    },
    {
      "title": "Iran war: What is happening on day 37 of US-Israeli attacks?",
      "url": "https://www.aljazeera.com/news/2026/4/5/iran-war-what-is-happening-on-day-37-of-us-israeli-attacks",
      "source": "Al Jazeera English",
      "publishedAt": "2026-04-05T07:45:48Z",
      "_cat": "lebanon",
      "_label": "Lebanon"
    },
    {
      "title": "Trump escalates feud with allies over Strait of Hormuz as energy crisis deepens",
      "url": "https://www.naturalnews.com/2026-04-05-trump-escalates-feud-allies-over-strait-hormuz.html",
      "source": "Naturalnews.com",
      "publishedAt": "2026-04-05T06:00:00Z",
      "_cat": "ukraine",
      "_label": "Ukraine"
    },
    {
      "title": "Putin's internet crackdown feels like 'the Soviet era but on steroids'",
      "url": "https://www.abc.net.au/news/2026-04-05/russia-internet-crackdown-vladimir-putin/106492926",
      "source": "ABC News (AU)",
      "publishedAt": "2026-04-05T04:15:07Z",
      "_cat": "ukraine",
      "_label": "Ukraine"
    },
    {
      "title": "Multipolarity As World Government 3.0 & Its Pied Pipers",
      "url": "https://www.activistpost.com/multipolarity-as-world-government-3-0-its-pied-pipers/",
      "source": "Activistpost.com",
      "publishedAt": "2026-04-05T01:36:00Z",
      "_cat": "ukraine",
      "_label": "Ukraine"
    },
    {
      "title": "What Beijing Is Learning From Operation Epic Fury",
      "url": "https://oilprice.com/Energy/Energy-General/What-Beijing-Is-Learning-From-Operation-Epic-Fury.html",
      "source": "OilPrice.com",
      "publishedAt": "2026-04-04T23:00:00Z",
      "_cat": "taiwan",
      "_label": "Taiwan"
    },
    {
      "title": "Battle for Bulgaria: The EU opens a new front in its election war",
      "url": "https://www.rt.com/news/637295-bulgaria-eu-election-hungary/",
      "source": "RT",
      "publishedAt": "2026-04-04T18:37:17Z",
      "_cat": "ukraine",
      "_label": "Ukraine"
    },
    {
      "title": "Young German men refusing military service",
      "url": "https://www.dw.com/en/young-german-men-refusing-military-service/a-76593888",
      "source": "DW (English)",
      "publishedAt": "2026-04-04T13:57:00Z",
      "_cat": "ukraine",
      "_label": "Ukraine"
    },
    {
      "title": "France preparing ‘war economy’ – Politico",
      "url": "https://www.rt.com/news/637283-france-preparing-war-economy/",
      "source": "RT",
      "publishedAt": "2026-04-04T13:34:05Z",
      "_cat": "ukraine",
      "_label": "Ukraine"
    },
    {
      "title": "Book Excerpt: The Info State--Politics in the Age of Total Control",
      "url": "https://www.realclearinvestigations.com/articles/2026/03/27/book_excerpt_the_information_state_-_politics_in_the_age_of_total_control_1172464.html",
      "source": "Realclearinvestigations.com",
      "publishedAt": "2026-04-04T12:40:12Z",
      "_cat": "ukraine",
      "_label": "Ukraine"
    },
    {
      "title": "Ukraine: 14 people killed in 'massive' Russian attack on 1,500th day of war",
      "url": "https://www.dw.com/en/ukraine-14-people-killed-in-massive-russian-attack-on-1500th-day-of-war/a-76652096",
      "source": "DW (English)",
      "publishedAt": "2026-04-04T06:51:00Z",
      "_cat": "ukraine",
      "_label": "Ukraine"
    }
  ]
}