{
  "updated": "2026-05-16T13:19:41Z",
  "count": 33,
  "articles": [
    {
      "title": "US-China summit exposes Trump's limits on Iran war, Taiwan",
      "url": "https://www.dw.com/en/us-china-summit-exposes-trumps-limits-on-iran-war-taiwan/a-77171942",
      "source": "DW (English)",
      "publishedAt": "2026-05-15T13:12:00Z",
      "_cat": "iran",
      "_label": "Iran War"
    },
    {
      "title": "The Pentagon Is Learning Drone Warfare From Ukraine",
      "url": "https://www.forbes.com/sites/davidkirichenko/2026/05/15/the-pentagon-is-learning-drone-warfare-from-ukraine/",
      "source": "Forbes",
      "publishedAt": "2026-05-15T13:00:00Z",
      "_cat": "ukraine",
      "_label": "Ukraine"
    },
    {
      "title": "Trump’s Lebanon Negotiations Are Breaking the Country",
      "url": "http://foreignpolicy.com/2026/05/15/trump-lebanon-beirut-israel-hezbollah-negotiations-ceasefire/",
      "source": "Foreign Policy",
      "publishedAt": "2026-05-15T12:29:40Z",
      "_cat": "lebanon",
      "_label": "Lebanon"
    },
    {
      "title": "Why the Iran conflict is becoming a problem for BRICS",
      "url": "https://www.aljazeera.com/news/2026/5/15/why-the-iran-conflict-is-becoming-a-problem-for-brics",
      "source": "Al Jazeera English",
      "publishedAt": "2026-05-15T12:21:12Z",
      "_cat": "iran",
      "_label": "Iran War"
    },
    {
      "title": "TANVI RATNA: How Trump’s NATO reset is becoming military reality",
      "url": "https://www.foxnews.com/opinion/tanvi-ratna-trumps-nato-reset-becoming-military-reality",
      "source": "Fox News",
      "publishedAt": "2026-05-15T12:20:55Z",
      "_cat": "ukraine",
      "_label": "Ukraine"
    },
    {
      "title": "What Kim Jong Un Really Fears: Outside Information",
      "url": "https://thediplomat.com/2026/05/what-kim-jong-un-really-fears-outside-information/",
      "source": "The Diplomat",
      "publishedAt": "2026-05-15T12:10:00Z",
      "_cat": "korea",
      "_label": "N. Korea"
    },
    {
      "title": "61% of Americans See Trump’s Iran War as ‘Mistake’, Far Outpacing Disapproval of Vietnam and Iraq: Poll",
      "url": "https://www.activistpost.com/61-of-americans-see-trumps-iran-war-as-mistake-far-outpacing-disapproval-of-vietnam-and-iraq-poll/",
      "source": "Activistpost.com",
      "publishedAt": "2026-05-15T12:05:00Z",
      "_cat": "iran",
      "_label": "Iran War"
    },
    {
      "title": "Israel strikes Lebanon amid US peace talks, ceasefire extension in doubt",
      "url": "https://cryptobriefing.com/israel-strikes-lebanon-amid-us-peace-talks-ceasefire-extension-in-doubt/",
      "source": "Crypto Briefing",
      "publishedAt": "2026-05-15T12:01:49Z",
      "_cat": "lebanon",
      "_label": "Lebanon"
    },
    {
      "title": "War worsens Lebanon's economic crisis with job losses, price gouging and slow business",
      "url": "https://abcnews.com/International/wireStory/war-worsens-lebanons-economic-crisis-job-losses-price-132990998",
      "source": "Abcnews.com",
      "publishedAt": "2026-05-15T12:00:33Z",
      "_cat": "lebanon",
      "_label": "Lebanon"
    },
    {
      "title": "UAE Rejects Tehran's 'Attempts To Justify' Its 'Terrorist Attacks'",
      "url": "https://www.globalsecurity.org/wmd/library/news/iran/2026/05/iran-260515-rferl05.htm",
      "source": "Globalsecurity.org",
      "publishedAt": "2026-05-15T12:00:00Z",
      "_cat": "iran",
      "_label": "Iran War"
    },
    {
      "title": "UAE failed to push GCC states to join a coordinated war against Iran: Report",
      "url": "https://www.globalsecurity.org/wmd/library/news/iran/2026/05/iran-260515-presstv02.htm",
      "source": "Globalsecurity.org",
      "publishedAt": "2026-05-15T12:00:00Z",
      "_cat": "iran",
      "_label": "Iran War"
    },
    {
      "title": "Iran slams neighbors' betrayal during US-Israeli aggression",
      "url": "https://www.globalsecurity.org/wmd/library/news/iran/2026/05/iran-260515-presstv05.htm",
      "source": "Globalsecurity.org",
      "publishedAt": "2026-05-15T12:00:00Z",
      "_cat": "iran",
      "_label": "Iran War"
    },
    {
      "title": "US Officials Warn End Of Ukraine War Could Heighten Russian Threat To Baltics",
      "url": "https://www.globalsecurity.org/wmd/library/news/ukraine/2026/05/ukraine-260515-rferl03.htm",
      "source": "Globalsecurity.org",
      "publishedAt": "2026-05-15T12:00:00Z",
      "_cat": "ukraine",
      "_label": "Ukraine"
    },
    {
      "title": "Iran War: Trump in China, Ship Seized in the Strait, War Powers Vote Comes This Close",
      "url": "https://www.nakedcapitalism.com/2026/05/iran-war-trump-xi-china-ships-strait-war-powers-vote.html",
      "source": "Nakedcapitalism.com",
      "publishedAt": "2026-05-15T10:30:59Z",
      "_cat": "iran",
      "_label": "Iran War"
    },
    {
      "title": "Israel escalates military actions in Lebanon, dims diplomatic meeting prospects",
      "url": "https://cryptobriefing.com/israel-escalates-military-actions-in-lebanon-dims-diplomatic-meeting-prospects/",
      "source": "Crypto Briefing",
      "publishedAt": "2026-05-15T10:20:20Z",
      "_cat": "lebanon",
      "_label": "Lebanon"
    },
    {
      "title": "India issues chair statement after BRICS meeting amid ‘differing views’ over West Asia conflict",
      "url": "https://indianexpress.com/article/india/india-issues-chair-statement-after-brics-meeting-amid-differing-views-over-west-asia-conflict-10691085/",
      "source": "The Indian Express",
      "publishedAt": "2026-05-15T10:03:44Z",
      "_cat": "iran",
      "_label": "Iran War"
    },
    {
      "title": "AUKUS and North Korea in the Indo-Pacific: 5 Years On",
      "url": "https://thediplomat.com/2026/05/aukus-and-north-korea-in-the-indo-pacific-5-years-on/",
      "source": "The Diplomat",
      "publishedAt": "2026-05-15T09:51:38Z",
      "_cat": "ukraine",
      "_label": "Ukraine"
    },
    {
      "title": "No stray drones in Finland, officials say",
      "url": "https://yle.fi/a/74-20226151",
      "source": "YLE News",
      "publishedAt": "2026-05-15T09:41:31Z",
      "_cat": "ukraine",
      "_label": "Ukraine"
    },
    {
      "title": "India ready to extend all possible support to bring peace in West Asia: PM Modi in UAE",
      "url": "https://economictimes.indiatimes.com/news/india/india-ready-to-extend-all-possible-support-to-bring-peace-in-west-asia-pm-modi-in-uae/articleshow/131113240.cms",
      "source": "The Times of India",
      "publishedAt": "2026-05-15T09:23:32Z",
      "_cat": "iran",
      "_label": "Iran War"
    },
    {
      "title": "IDF destroys Hezbollah launcher used to fire at Kiryat Shmona",
      "url": "https://www.israelnationalnews.com/news/427121",
      "source": "Israelnationalnews.com",
      "publishedAt": "2026-05-15T07:03:55Z",
      "_cat": "lebanon",
      "_label": "Lebanon"
    },
    {
      "title": "War worsens Lebanon's economic crisis with job losses, price gouging and slow business",
      "url": "https://abcnews.com/Business/wireStory/war-worsens-lebanons-economic-crisis-job-losses-price-132990999",
      "source": "Abcnews.com",
      "publishedAt": "2026-05-15T06:22:06Z",
      "_cat": "lebanon",
      "_label": "Lebanon"
    },
    {
      "title": "NATO scrambles fighter jets as Russia launches massive drone barrage toward Polish border, killing dozens in Ukraine",
      "url": "https://www.naturalnews.com/2026-05-15-nato-scrambles-fighter-jets-russia-launches-drones.html",
      "source": "Naturalnews.com",
      "publishedAt": "2026-05-15T06:00:00Z",
      "_cat": "ukraine",
      "_label": "Ukraine"
    },
    {
      "title": "US brokers between Israel, Lebanon, says progress with China on Mideast conflict",
      "url": "https://www.hurriyetdailynews.com/us-brokers-between-israel-lebanon-says-progress-with-china-on-mideast-conflict-222163",
      "source": "Hurriyet Daily News",
      "publishedAt": "2026-05-15T05:37:36Z",
      "_cat": "lebanon",
      "_label": "Lebanon"
    },
    {
      "title": "Israel strikes Lebanon, ceasefire extension prospects dim",
      "url": "https://cryptobriefing.com/israel-strikes-lebanon-ceasefire-extension-prospects-dim/",
      "source": "Crypto Briefing",
      "publishedAt": "2026-05-15T05:16:06Z",
      "_cat": "lebanon",
      "_label": "Lebanon"
    },
    {
      "title": "Beyond Ukraine, Russia is a grave threat to the West as a whole",
      "url": "https://www.americanthinker.com/blog/2026/05/beyond_ukraine_russia_is_a_grave_threat_to_the_west_as_a_whole.html",
      "source": "Americanthinker.com",
      "publishedAt": "2026-05-15T04:00:00Z",
      "_cat": "korea",
      "_label": "N. Korea"
    },
    {
      "title": "New Book Details How Washington and Moscow Forged a Framework for Security After the Cold War",
      "url": "https://www.hoover.org/new-book-details-how-washington-and-moscow-forged-framework-security-after-cold-war",
      "source": "Hoover.org",
      "publishedAt": "2026-05-15T00:00:00Z",
      "_cat": "ukraine",
      "_label": "Ukraine"
    },
    {
      "title": "Pope Leo slams Europe’s military buildup as ‘betrayal’ of diplomacy",
      "url": "https://www.rt.com/news/639987-pope-leo-eu-military-spending/",
      "source": "RT",
      "publishedAt": "2026-05-14T17:26:54Z",
      "_cat": "ukraine",
      "_label": "Ukraine"
    },
    {
      "title": "Can the NPT Survive Amid Global Disorder?",
      "url": "https://thediplomat.com/2026/05/can-the-npt-survive-amid-global-disorder/",
      "source": "The Diplomat",
      "publishedAt": "2026-05-14T16:04:00Z",
      "_cat": "ukraine",
      "_label": "Ukraine"
    },
    {
      "title": "Why Putin will have been watching the Trump-Xi summit nervously",
      "url": "https://theconversation.com/why-putin-will-have-been-watching-the-trump-xi-summit-nervously-282610",
      "source": "The Conversation Africa",
      "publishedAt": "2026-05-14T15:24:09Z",
      "_cat": "ukraine",
      "_label": "Ukraine"
    },
    {
      "title": "Trump-Xi Summit Leaves South Korea Navigating Familiar Pressures",
      "url": "https://thediplomat.com/2026/05/trump-xi-summit-leaves-south-korea-navigating-familiar-pressures/",
      "source": "The Diplomat",
      "publishedAt": "2026-05-14T14:20:00Z",
      "_cat": "korea",
      "_label": "N. Korea"
    },
    {
      "title": "North Korean operatives stole $2 billion last year—and financial firms are the next target",
      "url": "https://fortune.com/2026/05/14/north-korea-it-workers-stealing-billions-financial-firms-next-target-crowdstrike/",
      "source": "Fortune",
      "publishedAt": "2026-05-14T12:00:00Z",
      "_cat": "korea",
      "_label": "N. Korea"
    },
    {
      "title": "'Rare, meaningful': North Korean football team ventures into South",
      "url": "https://sports.yahoo.com/articles/rare-meaningful-north-korean-football-024835390.html",
      "source": "Yahoo Entertainment",
      "publishedAt": "2026-05-14T02:48:35Z",
      "_cat": "korea",
      "_label": "N. Korea"
    },
    {
      "title": "Xi Jinping Wants Taiwan For Free Trump Must Hold The Line",
      "url": "http://unherd.com/2026/05/xi-jinping-wants-taiwain-for-free/?edition=us",
      "source": "Unherd.com",
      "publishedAt": "2026-05-14T00:00:00Z",
      "_cat": "taiwan",
      "_label": "Taiwan"
    }
  ]
}