{
  "updated": "2026-06-10T20:28:07Z",
  "count": 38,
  "articles": [
    {
      "title": "Foreign Secretary statement on the Middle East: 9 June 2026",
      "url": "https://www.gov.uk/government/speeches/foreign-secretary-statement-on-the-middle-east-9-june-2026",
      "source": "Www.gov.uk",
      "publishedAt": "2026-06-09T20:13:39Z",
      "_cat": "iran",
      "_label": "Iran War"
    },
    {
      "title": "Strategic mastery: Israel's measured response to Iranian aggression",
      "url": "https://www.israelnationalnews.com/news/428385",
      "source": "Israelnationalnews.com",
      "publishedAt": "2026-06-09T20:11:38Z",
      "_cat": "lebanon",
      "_label": "Lebanon"
    },
    {
      "title": "Israel Launches New Strikes Against Lebanon While Trump Claims Iran Deal Is Close",
      "url": "https://www.shtfplan.com/war/israel-launches-new-strikes-against-lebanon-while-trump-claims-iran-deal-is-close",
      "source": "Shtfplan.com",
      "publishedAt": "2026-06-09T20:00:28Z",
      "_cat": "iran",
      "_label": "Iran War"
    },
    {
      "title": "Israel conducts air strikes in Tyre, killing at least 13 despite Iranian warning",
      "url": "https://cryptobriefing.com/israel-air-strikes-tyre-lebanon-iran-warning/",
      "source": "Crypto Briefing",
      "publishedAt": "2026-06-09T19:55:08Z",
      "_cat": "lebanon",
      "_label": "Lebanon"
    },
    {
      "title": "Xi hosted Trump and Putin in China, but he boarded a plane for Kim",
      "url": "https://www.abc.net.au/news/2026-06-10/xi-jinping-s-trip-to-north-korea-kim-jong-un-unusual/106773414",
      "source": "ABC News (AU)",
      "publishedAt": "2026-06-09T19:53:02Z",
      "_cat": "korea",
      "_label": "N. Korea"
    },
    {
      "title": "Oil Futures Volatility Returns",
      "url": "https://www.rigzone.com/news/wire/oil_futures_volatility_returns-09-jun-2026-183888-article/",
      "source": "Rigzone",
      "publishedAt": "2026-06-09T19:47:29Z",
      "_cat": "iran",
      "_label": "Iran War"
    },
    {
      "title": "Ukraine Is Ready to Share Drone Technology with Nordic and Baltic Countries, Zelenskyy Says",
      "url": "https://military.com/ukraine-is-ready-to-share-drone-technology-with-nordic-and-baltic-countries-zelenskyy-says",
      "source": "Military.com",
      "publishedAt": "2026-06-09T19:06:43Z",
      "_cat": "ukraine",
      "_label": "Ukraine"
    },
    {
      "title": "Israel Strikes Hezbollah Targets in Lebanese City of Tyre",
      "url": "https://legalinsurrection.com/2026/06/israel-strikes-hezbollah-targets-in-lebanese-city-of-tyre/",
      "source": "Legalinsurrection.com",
      "publishedAt": "2026-06-09T19:00:15Z",
      "_cat": "lebanon",
      "_label": "Lebanon"
    },
    {
      "title": "Fears of Escalation After Trump Says US Must ‘Respond’ to Iran Downing Apache Helicopter",
      "url": "https://www.commondreams.org/news/trump-respond-iran-helicopter",
      "source": "Common Dreams",
      "publishedAt": "2026-06-09T18:55:51Z",
      "_cat": "iran",
      "_label": "Iran War"
    },
    {
      "title": "Trump vows response after Iran shoots down US helicopter",
      "url": "https://punchng.com/trump-vows-response-after-iran-shoots-down-us-helicopter/",
      "source": "The Punch",
      "publishedAt": "2026-06-09T18:51:59Z",
      "_cat": "iran",
      "_label": "Iran War"
    },
    {
      "title": "TRUMP: Iran responsible for downing American helicopter. USA MUST respond...",
      "url": "https://abc7.com/post/iran-war-update-trump-says-pilots-are-fine-us-helicopter-crashes-strait-hormuz/19261063/",
      "source": "KABC-TV",
      "publishedAt": "2026-06-09T18:00:16Z",
      "_cat": "lebanon",
      "_label": "Lebanon"
    },
    {
      "title": "Coffee Break: Armed Madhouse – Israel’s Buffer Defense Quandary",
      "url": "https://www.nakedcapitalism.com/2026/06/coffee-break-armed-madhouse-israels-buffer-defense-quandary.html",
      "source": "Nakedcapitalism.com",
      "publishedAt": "2026-06-09T18:00:10Z",
      "_cat": "lebanon",
      "_label": "Lebanon"
    },
    {
      "title": "‘Anything but normal’: Uncertainty as Iranians try to get by amid US war",
      "url": "https://www.aljazeera.com/news/2026/6/9/anything-but-normal-uncertainty-as-iranians-try-to-get-by-amid-us-war",
      "source": "Al Jazeera English",
      "publishedAt": "2026-06-09T17:59:23Z",
      "_cat": "iran",
      "_label": "Iran War"
    },
    {
      "title": "Israel strikes Tyre, Lebanon, killing at least eight after first-ever full evacuation order",
      "url": "https://cryptobriefing.com/israel-strikes-tyre-lebanon-crypto-impact/",
      "source": "Crypto Briefing",
      "publishedAt": "2026-06-09T17:58:14Z",
      "_cat": "lebanon",
      "_label": "Lebanon"
    },
    {
      "title": "Will Israel's troops take over more of southern Lebanon?",
      "url": "https://www.dw.com/en/will-israels-troops-take-over-more-of-southern-lebanon/a-77478170",
      "source": "DW (English)",
      "publishedAt": "2026-06-09T17:48:00Z",
      "_cat": "lebanon",
      "_label": "Lebanon"
    },
    {
      "title": "Xi's Visit Signifies China Recognizing North Korea's Nuclear Status – Expert",
      "url": "https://sputnikglobe.com/20260609/xis-visit-signifies-china-recognizing-north-koreas-nuclear-status-expert-1124290177.html",
      "source": "Sputnikglobe.com",
      "publishedAt": "2026-06-09T17:46:21Z",
      "_cat": "korea",
      "_label": "N. Korea"
    },
    {
      "title": "Trump Orders US Response After Iran Downs Apache Helicopter",
      "url": "https://dailycaller.com/2026/06/09/trump-orders-us-attack-after-iran-downs-apache-helicopter/",
      "source": "The Daily Caller",
      "publishedAt": "2026-06-09T17:45:35Z",
      "_cat": "iran",
      "_label": "Iran War"
    },
    {
      "title": "NATO country to stop supplying arms to Ukraine",
      "url": "https://www.rt.com/news/641312-bulgaria-ends-weapons-shipments-ukraine/",
      "source": "RT",
      "publishedAt": "2026-06-09T17:24:38Z",
      "_cat": "ukraine",
      "_label": "Ukraine"
    },
    {
      "title": "Trump says Iran shot down US military helicopter over Strait of Hormuz and vows to respond",
      "url": "https://www.thejournal.ie/iran-shot-down-apache-helicopter-7065434-Jun2026/",
      "source": "TheJournal.ie",
      "publishedAt": "2026-06-09T17:15:34Z",
      "_cat": "iran",
      "_label": "Iran War"
    },
    {
      "title": "EU proposes entry ban for Russians who fought in Ukraine",
      "url": "https://www.dw.com/en/eu-plans-russia-entry-ban-war-in-ukraine/a-77474536",
      "source": "DW (English)",
      "publishedAt": "2026-06-09T17:14:00Z",
      "_cat": "ukraine",
      "_label": "Ukraine"
    },
    {
      "title": "EU proposes entry ban for Russian Ukraine combatants in new sanctions package",
      "url": "https://www.dw.com/en/eu-proposes-entry-ban-for-russian-ukraine-combatants-in-new-sanctions-package/a-77474536",
      "source": "DW (English)",
      "publishedAt": "2026-06-09T17:14:00Z",
      "_cat": "ukraine",
      "_label": "Ukraine"
    },
    {
      "title": "Israel kills eight in strike on Lebanon; US rescues helicopter crew from Hormuz",
      "url": "https://www.channelnewsasia.com/world/israel-kills-eight-in-strike-lebanon-us-rescues-helicopter-crew-hormuz-6171926",
      "source": "CNA",
      "publishedAt": "2026-06-09T17:05:22Z",
      "_cat": "iran",
      "_label": "Iran War"
    },
    {
      "title": "EU Shift Into Military Bloc Will Erode Its Prosperity for Generations",
      "url": "https://sputnikglobe.com/20260609/eu-shift-into-military-bloc-will-erode-its-prosperity-for-generations-1124289753.html",
      "source": "Sputnikglobe.com",
      "publishedAt": "2026-06-09T16:55:16Z",
      "_cat": "ukraine",
      "_label": "Ukraine"
    },
    {
      "title": "China, North Korea boast better ties after Xi-Kim talks",
      "url": "https://www.dw.com/en/china-north-korea-boast-better-ties-after-xi-kim-talks/a-77477935",
      "source": "DW (English)",
      "publishedAt": "2026-06-09T14:57:00Z",
      "_cat": "korea",
      "_label": "N. Korea"
    },
    {
      "title": "China, North Korea to expand cooperation after Xi-Kim talks",
      "url": "https://www.dw.com/en/china-north-korea-xi-jinping-kim-jong-un-relationship-nuclear-program/a-77477935",
      "source": "DW (English)",
      "publishedAt": "2026-06-09T14:57:00Z",
      "_cat": "korea",
      "_label": "N. Korea"
    },
    {
      "title": "Bulgaria's new government to stop supplying weapons to Ukraine",
      "url": "https://abcnews.com/International/wireStory/bulgarias-new-government-stop-supplying-weapons-ukraine-133713219",
      "source": "Abcnews.com",
      "publishedAt": "2026-06-09T14:56:34Z",
      "_cat": "ukraine",
      "_label": "Ukraine"
    },
    {
      "title": "Russia deflects drones into Finland for 'gratifying effect', expert warns",
      "url": "https://yle.fi/a/74-20230583",
      "source": "YLE News",
      "publishedAt": "2026-06-09T13:30:35Z",
      "_cat": "ukraine",
      "_label": "Ukraine"
    },
    {
      "title": "Minister of Defence Antti Häkkänen's speech at the meeting of the Council of Europe's Committee on Social Inclusion and Human Dignity",
      "url": "https://www.globalsecurity.org/military/library/news/2026/06/mil-260609-finmod01.htm",
      "source": "Globalsecurity.org",
      "publishedAt": "2026-06-09T12:00:00Z",
      "_cat": "ukraine",
      "_label": "Ukraine"
    },
    {
      "title": "Day 1,567 of WW3. Muscovites start to panic as UAF drones roam freely in russian skies. Best Korea's economy booms from supporting russia, and Lapdog declares Orcistan will resolve the war on the battlefield. This is your Tuesday Ukraine War thread [News]",
      "url": "https://www.fark.com/comments/14093352/Day-1567-of-WW3-Muscovites-start-to-panic-as-UAF-drones-roam-freely-in-russian-skies-Best-Koreas-economy-booms-from-supporting-russia-Lapdog-declares-Orcistan-will-resolve-war-on-battlefield-This-is-your-Tuesday-Ukraine-War-thread",
      "source": "Fark.com",
      "publishedAt": "2026-06-09T12:00:00Z",
      "_cat": "ukraine",
      "_label": "Ukraine"
    },
    {
      "title": "China's President Xi returns home after closely watched trip to North Korea",
      "url": "https://abcnews.com/International/wireStory/chinas-president-xi-returns-home-after-closely-watched-133706632",
      "source": "Abcnews.com",
      "publishedAt": "2026-06-09T11:47:17Z",
      "_cat": "korea",
      "_label": "N. Korea"
    },
    {
      "title": "Ukraine's Zelenskyy arrives in Estonia to attend Nordic-Baltic summit",
      "url": "https://abcnews.com/International/wireStory/ukraines-zelenskyy-arrives-estonia-attend-nordic-baltic-summit-133705259",
      "source": "Abcnews.com",
      "publishedAt": "2026-06-09T11:44:42Z",
      "_cat": "ukraine",
      "_label": "Ukraine"
    },
    {
      "title": "Analysis: Chinese President Xi's silence on nuclear arms is a gift to North Korea's Kim Jong Un",
      "url": "https://abcnews.com/Business/wireStory/analysis-chinese-president-xis-silence-nuclear-arms-gift-133707061",
      "source": "Abcnews.com",
      "publishedAt": "2026-06-09T11:44:31Z",
      "_cat": "korea",
      "_label": "N. Korea"
    },
    {
      "title": "Analysis: Chinese President Xi's silence on nuclear arms is a gift to North Korea's Kim Jong Un",
      "url": "https://www.seattlepi.com/news/world/article/analysis-chinese-president-xi-s-silence-on-22297187.php",
      "source": "seattlepi.com",
      "publishedAt": "2026-06-09T11:10:32Z",
      "_cat": "korea",
      "_label": "N. Korea"
    },
    {
      "title": "The Israel-India Partnership",
      "url": "https://www.hoover.org/research/israel-india-partnership",
      "source": "Hoover.org",
      "publishedAt": "2026-06-09T00:00:00Z",
      "_cat": "nuclear",
      "_label": "Nuclear"
    },
    {
      "title": "Beijing’s Military Shadow Looms Large Over Key Taiwan Tech Conference",
      "url": "https://dailycaller.com/2026/06/08/beijings-military-shadow-looms-large-over-computex-taipei-conference/",
      "source": "The Daily Caller",
      "publishedAt": "2026-06-08T17:52:07Z",
      "_cat": "taiwan",
      "_label": "Taiwan"
    },
    {
      "title": "Report: China's maritime outposts could distract Taiwan's allies if Beijing invades",
      "url": "https://www.globalsecurity.org/wmd/library/news/taiwan/2026/taiwan-260608-rfa01.htm",
      "source": "Globalsecurity.org",
      "publishedAt": "2026-06-08T12:00:00Z",
      "_cat": "taiwan",
      "_label": "Taiwan"
    },
    {
      "title": "Trump and Netanyahu: The Odd Couple",
      "url": "https://www.counterpunch.org/2026/06/08/trump-and-netanyahu-the-odd-couple/",
      "source": "CounterPunch",
      "publishedAt": "2026-06-08T05:55:40Z",
      "_cat": "nuclear",
      "_label": "Nuclear"
    },
    {
      "title": "When Xi Jinping meets Kim Jong-un",
      "url": "https://www.irishtimes.com/world/2026/06/08/why-xi-jinping-is-meeting-kim-jong-un-in-pyongyang/",
      "source": "The Irish Times",
      "publishedAt": "2026-06-08T05:37:52Z",
      "_cat": "nuclear",
      "_label": "Nuclear"
    }
  ]
}